ColabKit/__init__.py
ColabKit/media.py
ColabKit/record.py
ColabKit/template.py
ColabKit/utils.py
ColabKit/widget.py
ColabKit-0.0.1.dist-info/LICENSE
ColabKit-0.0.1.dist-info/METADATA
ColabKit-0.0.1.dist-info/WHEEL
ColabKit-0.0.1.dist-info/top_level.txt
ColabKit-0.0.1.dist-info/RECORD
