Metadata-Version: 2.1
Name: ColabKit
Version: 0.0.1
Summary: ColabKit: A Python library with essential tools to streamline your work in Google Colab, including functions for managing media, recording audio, generating interactive widgets, and performing common operations in the Colab environment.
Home-page: https://github.com/wipodev/ColabKit
Author: Wipodev
Author-email: ajwipo@gmail.com
License: MIT
Project-URL: Documentation, https://github.com/wipodev/ColabKit/blob/main/README.md
Project-URL: Source, https://github.com/wipodev/ColabKit
Project-URL: Bug Tracker, https://github.com/wipodev/ColabKit/issues
Keywords: google colaboratory ColabKit wipo wipodev functions Audio Recording Widgets Media Video Colab Python Tools
Classifier: Programming Language :: Python :: 3
Classifier: License :: OSI Approved :: MIT License
Classifier: Operating System :: OS Independent
Requires-Python: >=3.10
License-File: LICENSE
Requires-Dist: ipywidgets
Requires-Dist: ffmpeg-python
Requires-Dist: scipy
